localstream/ConfigFile.py
localstream/Fragmenter.py
localstream/PrivoxyManager.py
localstream/SystemProxy.py
localstream/__init__.py
localstream/__main__.py
localstream/autostart.py
localstream/cli.py
localstream/config.py
localstream/connection.py
localstream/downloader.py
localstream/speedtest.py
localstream-1.0.6.dist-info/licenses/LICENSE
localstream-1.0.6.dist-info/METADATA
localstream-1.0.6.dist-info/WHEEL
localstream-1.0.6.dist-info/entry_points.txt
localstream-1.0.6.dist-info/top_level.txt
localstream-1.0.6.dist-info/RECORD
