Metadata-Version: 2.4
Name: localstream
Version: 1.0.6
Summary: Python CLI client for slipstream-rust DNS tunnel
Author: LocalStream Team
License: Apache-2.0
Keywords: dns,tunnel,vpn,slipstream,cli
Classifier: Development Status :: 4 - Beta
Classifier: Environment :: Console
Classifier: Intended Audience :: End Users/Desktop
Classifier: License :: OSI Approved :: Apache Software License
Classifier: Operating System :: Microsoft :: Windows
Classifier: Programming Language :: Python :: 3.13
Classifier: Topic :: Internet :: Proxy Servers
Requires-Python: >=3.11
License-File: LICENSE
Requires-Dist: requests>=2.31.0
Requires-Dist: colorama>=0.4.6
Requires-Dist: cryptography>=42.0.0
Provides-Extra: gui
Requires-Dist: fastapi>=0.104.0; extra == "gui"
Requires-Dist: uvicorn>=0.24.0; extra == "gui"
Requires-Dist: pydantic>=2.5.0; extra == "gui"
Dynamic: license-file
